autofff/__init__.py
autofff/__main__.py
autofff/config.py
autofff/generator.py
autofff/scanner.py
autofff/utils.py
autofff-0.5.dist-info/LICENSE
autofff-0.5.dist-info/METADATA
autofff-0.5.dist-info/WHEEL
autofff-0.5.dist-info/entry_points.txt
autofff-0.5.dist-info/RECORD
