Metadata-Version: 2.1
Name: autofff
Version: 0.5
Summary: Auto-generate FFF fake definitions for C API header files
Home-page: https://github.com/ChiefGokhlayeh/autofff
License: MIT
Author: Andreas Baulig
Author-email: free.geronimo@hotmail.de
Requires-Python: >=3.10,<4.0
Classifier: Development Status :: 4 - Beta
Classifier: Intended Audience :: Developers
Classifier: License :: OSI Approved :: MIT License
Classifier: Operating System :: OS Independent
Classifier: Programming Language :: C
Classifier: Programming Language :: C++
Classifier: Programming Language :: Python :: 3
Classifier: Programming Language :: Python :: 3.10
Classifier: Programming Language :: Python :: 3.11
Classifier: Programming Language :: Python :: 3.10
Classifier: Programming Language :: Python :: 3.6
Classifier: Programming Language :: Python :: 3.7
Classifier: Programming Language :: Python :: 3.8
Classifier: Programming Language :: Python :: 3.9
Classifier: Topic :: Software Development :: Code Generators
Classifier: Topic :: Software Development :: Testing
Requires-Dist: configobj (>=5.0.8,<6.0.0)
Requires-Dist: overrides (>=6.5,<8.0)
Requires-Dist: phmutest (>=0.0.3,<0.0.4)
Requires-Dist: pycparser (>=2.21,<3.0)
Requires-Dist: validator (>=0.7.1,<0.8.0)
Project-URL: Repository, https://github.com/ChiefGokhlayeh/autofff
